darknet.py
darknet_hankai-3.0.0.dist-info/METADATA
darknet_hankai-3.0.0.dist-info/WHEEL
darknet_hankai-3.0.0.dist-info/top_level.txt
darknet_hankai-3.0.0.dist-info/RECORD
