Metadata-Version: 2.2
Name: darknet-hankai
Version: 3.0.0
Summary: Python bindings for Darknet
License: Apache-2.0
Classifier: Programming Language :: Python :: 3
Classifier: Operating System :: OS Independent
Classifier: License :: OSI Approved :: Apache Software License
Dynamic: classifier
Dynamic: license
Dynamic: summary
